jsonast/__init__.py
jsonast/jsonalizer.py
jsonast/parser.py
jsonast/parser_json.py
jsonast/tags.py
jsonast-0.0.4.dist-info/WHEEL
jsonast-0.0.4.dist-info/METADATA
jsonast-0.0.4.dist-info/RECORD
