Metadata-Version: 2.1
Name: jsonast
Version: 0.0.4
Summary: 
Home-page: https://github.com/sasano8/jsonast
License: MIT
Author: sasano8
Author-email: y-sasahara@ys-method.com
Requires-Python: >=3.8,<=3.10
Classifier: License :: OSI Approved :: MIT License
Classifier: Programming Language :: Python :: 3
Classifier: Programming Language :: Python :: 3.8
Requires-Dist: jsonml (>=0.0.3,<0.0.4)
Project-URL: Repository, https://github.com/sasano8/jsonast
